kslhub/__init__.py
kslhub/_version.py
kslhub/batchspawner.py
kslhub/kslhub_frontend.py
kslhub/otp_authenticator.py
kslhub/scan_template.py
kslhub/ssh_authenticator.py
kslhub/wrapspawner.py
kslhub-0.0.19.data/data/lib/python3.7/site-packages/jupyterhub/orm.py
kslhub-0.0.19.data/data/lib/python3.7/site-packages/jupyterhub/spawner.py
kslhub-0.0.19.data/data/lib/python3.7/site-packages/jupyterhub/handlers/login.py
kslhub-0.0.19.data/data/lib/python3.7/site-packages/jupyterhub/handlers/pages.py
kslhub-0.0.19.data/data/lib/python3.7/site-packages/jupyterhub/oauth/provider.py
kslhub-0.0.19.data/data/lib/python3.7/site-packages/jupyterhub/services/auth.py
kslhub-0.0.19.data/data/share/kslhub/config/default.py
kslhub-0.0.19.data/data/share/kslhub/config/docker_prod.py
kslhub-0.0.19.data/data/share/kslhub/config/docker_slurm.py
kslhub-0.0.19.data/data/share/kslhub/config/on_host.py
kslhub-0.0.19.data/data/share/kslhub/config/shaheen.py
kslhub-0.0.19.data/data/share/kslhub/config/sk.py
kslhub-0.0.19.data/data/share/kslhub/config/sk_prod.py
kslhub-0.0.19.data/data/share/kslhub/job_templates/00 - lab.template
kslhub-0.0.19.data/data/share/kslhub/job_templates/01 - lab_bis.template
kslhub-0.0.19.data/data/share/kslhub/job_templates/02 - job on docker.template
kslhub-0.0.19.data/data/share/kslhub/job_templates/03 - debug_1_core_30_minutes.template
kslhub-0.0.19.data/data/share/kslhub/job_templates/04 - job_4_core_24_hours.template
kslhub-0.0.19.data/data/share/kslhub/job_templates/05 - debug_1_core_2_minutes.template
kslhub-0.0.19.data/data/share/kslhub/job_templates/0a - lab.template2
kslhub-0.0.19.data/data/share/kslhub/templates/404.html
kslhub-0.0.19.data/data/share/kslhub/templates/admin.html
kslhub-0.0.19.data/data/share/kslhub/templates/error.html
kslhub-0.0.19.data/data/share/kslhub/templates/home.html
kslhub-0.0.19.data/data/share/kslhub/templates/login.html
kslhub-0.0.19.data/data/share/kslhub/templates/logout.html
kslhub-0.0.19.dist-info/AUTHORS
kslhub-0.0.19.dist-info/LICENSE.txt
kslhub-0.0.19.dist-info/METADATA
kslhub-0.0.19.dist-info/WHEEL
kslhub-0.0.19.dist-info/entry_points.txt
kslhub-0.0.19.dist-info/top_level.txt
kslhub-0.0.19.dist-info/RECORD
