Metadata-Version: 2.1
Name: kslhub
Version: 0.0.19
Summary: klshub - a datahub based on jupyterhub 
Home-page: http://kslhub.readthedocs.io
Author: Samuel KORTAS
Author-email: samuel.kortas@kaust.edu.sa
Maintainer: Samuel KORTAS
Maintainer-email: samuel.kortas@kaust.edu.sa
License: UNKNOWN
Keywords: scheduler extension workflow parametric
Platform: UNKNOWN
Classifier: Development Status :: 3 - Alpha
Classifier: Environment :: Console
Classifier: Intended Audience :: Science/Research
Classifier: Topic :: Software Development :: Build Tools
Classifier: License :: OSI Approved :: BSD License
Classifier: Programming Language :: Python :: 3
Classifier: Programming Language :: Python :: 3.4
Classifier: Programming Language :: Python :: 3.5
Classifier: Programming Language :: Python :: 3.6
Classifier: Operating System :: POSIX
Classifier: Topic :: Software Development :: Libraries :: Python Modules
Classifier: Topic :: System :: Clustering
Classifier: Topic :: System :: Distributed Computing
Classifier: Topic :: Utilities
Requires-Python: >=3.6
Requires-Dist: cython
Requires-Dist: notebook
Requires-Dist: pandas
Requires-Dist: matplotlib
Requires-Dist: sympy
Requires-Dist: bash-kernel
Requires-Dist: yapf
Requires-Dist: jupyter-contrib-nbextensions
Requires-Dist: jupyter-nbextensions-configurator
Requires-Dist: ipywidgets
Requires-Dist: dask
Requires-Dist: toolz
Requires-Dist: cloudpickle
Requires-Dist: distributed
Requires-Dist: dockerspawner
Requires-Dist: ipyparallel
Requires-Dist: six (>-1.11.0)
Requires-Dist: alembic
Requires-Dist: async-generator (>=1.8)
Requires-Dist: entrypoints
Requires-Dist: traitlets (>=4.3.2)
Requires-Dist: tornado (>=5.0)
Requires-Dist: jinja2
Requires-Dist: oauthlib (<3,>=2)
Requires-Dist: pamela
Requires-Dist: paramiko
Requires-Dist: python-dateutil
Requires-Dist: SQLAlchemy (>=1.1)
Requires-Dist: requests
Requires-Dist: prometheus-client (>=0.0.21)
Requires-Dist: jupyterhub (==0.9.4)
Requires-Dist: jupyterlab
Requires-Dist: certipy (>=0.1.2)
